MANIFEST.in
README.rst
setup.py
src/expbackoff/__init__.py
src/expbackoff.egg-info/PKG-INFO
src/expbackoff.egg-info/SOURCES.txt
src/expbackoff.egg-info/dependency_links.txt
src/expbackoff.egg-info/top_level.txt