Metadata-Version: 1.1
Name: expbackoff
Version: 0.1.0
Summary: Exponential backoff with jitter.
Home-page: https://github.com/nathforge/expbackoff
Author: Nathan Reynolds
Author-email: email@nreynolds.co.uk
License: UNKNOWN
Platform: UNKNOWN
Classifier: Development Status :: 4 - Beta
Classifier: Intended Audience :: Developers
Classifier: Topic :: Software Development
Classifier: License :: OSI Approved :: MIT License
Classifier: Programming Language :: Python :: 2.7
